c7n_azure/__init__.py
c7n_azure/azure_events.py
c7n_azure/constants.py
c7n_azure/entry.py
c7n_azure/filters.py
c7n_azure/function.py
c7n_azure/function_package.py
c7n_azure/functionapp_utils.py
c7n_azure/graph_utils.py
c7n_azure/handler.py
c7n_azure/output.py
c7n_azure/policy.py
c7n_azure/provider.py
c7n_azure/query.py
c7n_azure/session.py
c7n_azure/storage_utils.py
c7n_azure/tags.py
c7n_azure/utils.py
c7n_azure/actions/__init__.py
c7n_azure/actions/base.py
c7n_azure/actions/delete.py
c7n_azure/actions/firewall.py
c7n_azure/actions/lock.py
c7n_azure/actions/logic_app.py
c7n_azure/actions/notify.py
c7n_azure/actions/tagging.py
c7n_azure/container_host/__init__.py
c7n_azure/container_host/host.py
c7n_azure/container_host/modes.py
c7n_azure/provisioning/__init__.py
c7n_azure/provisioning/app_insights.py
c7n_azure/provisioning/app_service_plan.py
c7n_azure/provisioning/autoscale.py
c7n_azure/provisioning/deployment_unit.py
c7n_azure/provisioning/function_app.py
c7n_azure/provisioning/resource_group.py
c7n_azure/provisioning/storage_account.py
c7n_azure/resources/__init__.py
c7n_azure/resources/access_control.py
c7n_azure/resources/aci.py
c7n_azure/resources/advisor.py
c7n_azure/resources/afd_custom_domain.py
c7n_azure/resources/afd_endpoint.py
c7n_azure/resources/alertlogs.py
c7n_azure/resources/apimanagement.py
c7n_azure/resources/app_configuration.py
c7n_azure/resources/app_gateway.py
c7n_azure/resources/app_service_environment.py
c7n_azure/resources/appinsights.py
c7n_azure/resources/appserviceplan.py
c7n_azure/resources/arm.py
c7n_azure/resources/automation_account.py
c7n_azure/resources/backup_vault.py
c7n_azure/resources/bastion_host.py
c7n_azure/resources/batch.py
c7n_azure/resources/cdn.py
c7n_azure/resources/cdn_custom_domain.py
c7n_azure/resources/cdn_endpoint.py
c7n_azure/resources/cognitive_service.py
c7n_azure/resources/container_registry.py
c7n_azure/resources/container_service.py
c7n_azure/resources/cosmos_db.py
c7n_azure-0.7.48.dist-info/METADATA
c7n_azure-0.7.48.dist-info/WHEEL
c7n_azure-0.7.48.dist-info/RECORD
